{
  "site": "ballsdeep",
  "date": "2026-02-27",
  "gathered_at": "2026-02-27T15:44:59.568918",
  "status": "pending_processing",
  "games": [
    {
      "name": "Charlotte Hornets at Indiana Pacers",
      "short_name": "CHA @ IND",
      "status": "Final",
      "sport": "nba",
      "home_team": "Indiana Pacers",
      "home_score": "109",
      "away_team": "Charlotte Hornets",
      "away_score": "133",
      "is_blowout": true
    },
    {
      "name": "Miami Heat at Philadelphia 76ers",
      "short_name": "MIA @ PHI",
      "status": "Final",
      "sport": "nba",
      "home_team": "Philadelphia 76ers",
      "home_score": "124",
      "away_team": "Miami Heat",
      "away_score": "117",
      "is_blowout": false
    },
    {
      "name": "Washington Wizards at Atlanta Hawks",
      "short_name": "WSH @ ATL",
      "status": "Final",
      "sport": "nba",
      "home_team": "Atlanta Hawks",
      "home_score": "126",
      "away_team": "Washington Wizards",
      "away_score": "96",
      "is_blowout": true
    },
    {
      "name": "San Antonio Spurs at Brooklyn Nets",
      "short_name": "SA @ BKN",
      "status": "Final",
      "sport": "nba",
      "home_team": "Brooklyn Nets",
      "home_score": "110",
      "away_team": "San Antonio Spurs",
      "away_score": "126",
      "is_blowout": false
    },
    {
      "name": "Houston Rockets at Orlando Magic",
      "short_name": "HOU @ ORL",
      "status": "Final",
      "sport": "nba",
      "home_team": "Orlando Magic",
      "home_score": "108",
      "away_team": "Houston Rockets",
      "away_score": "113",
      "is_blowout": false
    },
    {
      "name": "Portland Trail Blazers at Chicago Bulls",
      "short_name": "POR @ CHI",
      "status": "Final",
      "sport": "nba",
      "home_team": "Chicago Bulls",
      "home_score": "112",
      "away_team": "Portland Trail Blazers",
      "away_score": "121",
      "is_blowout": false
    },
    {
      "name": "Sacramento Kings at Dallas Mavericks",
      "short_name": "SAC @ DAL",
      "status": "Final",
      "sport": "nba",
      "home_team": "Dallas Mavericks",
      "home_score": "121",
      "away_team": "Sacramento Kings",
      "away_score": "130",
      "is_blowout": false
    },
    {
      "name": "Los Angeles Lakers at Phoenix Suns",
      "short_name": "LAL @ PHX",
      "status": "Final",
      "sport": "nba",
      "home_team": "Phoenix Suns",
      "home_score": "113",
      "away_team": "Los Angeles Lakers",
      "away_score": "110",
      "is_blowout": false
    },
    {
      "name": "New Orleans Pelicans at Utah Jazz",
      "short_name": "NO @ UTAH",
      "status": "Final",
      "sport": "nba",
      "home_team": "Utah Jazz",
      "home_score": "118",
      "away_team": "New Orleans Pelicans",
      "away_score": "129",
      "is_blowout": false
    },
    {
      "name": "Minnesota Timberwolves at LA Clippers",
      "short_name": "MIN @ LAC",
      "status": "Final",
      "sport": "nba",
      "home_team": "LA Clippers",
      "home_score": "88",
      "away_team": "Minnesota Timberwolves",
      "away_score": "94",
      "is_blowout": false
    },
    {
      "name": "Seattle Seahawks at New England Patriots",
      "short_name": "SEA VS NE",
      "status": "Final",
      "sport": "nfl",
      "home_team": "New England Patriots",
      "home_score": "13",
      "away_team": "Seattle Seahawks",
      "away_score": "29",
      "is_blowout": true
    },
    {
      "name": "Columbus Blue Jackets at Boston Bruins",
      "short_name": "CBJ @ BOS",
      "status": "Final",
      "sport": "nhl",
      "home_team": "Boston Bruins",
      "home_score": "4",
      "away_team": "Columbus Blue Jackets",
      "away_score": "2",
      "is_blowout": false
    },
    {
      "name": "New York Islanders at Montreal Canadiens",
      "short_name": "NYI @ MTL",
      "status": "Final",
      "sport": "nhl",
      "home_team": "Montreal Canadiens",
      "home_score": "3",
      "away_team": "New York Islanders",
      "away_score": "4",
      "is_blowout": false
    },
    {
      "name": "Detroit Red Wings at Ottawa Senators",
      "short_name": "DET @ OTT",
      "status": "Final",
      "sport": "nhl",
      "home_team": "Ottawa Senators",
      "home_score": "1",
      "away_team": "Detroit Red Wings",
      "away_score": "2",
      "is_blowout": false
    },
    {
      "name": "Toronto Maple Leafs at Florida Panthers",
      "short_name": "TOR @ FLA",
      "status": "Final",
      "sport": "nhl",
      "home_team": "Florida Panthers",
      "home_score": "5",
      "away_team": "Toronto Maple Leafs",
      "away_score": "1",
      "is_blowout": false
    },
    {
      "name": "New Jersey Devils at Pittsburgh Penguins",
      "short_name": "NJ @ PIT",
      "status": "Final",
      "sport": "nhl",
      "home_team": "Pittsburgh Penguins",
      "home_score": "4",
      "away_team": "New Jersey Devils",
      "away_score": "1",
      "is_blowout": false
    },
    {
      "name": "Tampa Bay Lightning at Carolina Hurricanes",
      "short_name": "TB @ CAR",
      "status": "Final",
      "sport": "nhl",
      "home_team": "Carolina Hurricanes",
      "home_score": "5",
      "away_team": "Tampa Bay Lightning",
      "away_score": "4",
      "is_blowout": false
    },
    {
      "name": "Philadelphia Flyers at New York Rangers",
      "short_name": "PHI @ NYR",
      "status": "Final",
      "sport": "nhl",
      "home_team": "New York Rangers",
      "home_score": "2",
      "away_team": "Philadelphia Flyers",
      "away_score": "3",
      "is_blowout": false
    },
    {
      "name": "Seattle Kraken at St. Louis Blues",
      "short_name": "SEA @ STL",
      "status": "Final",
      "sport": "nhl",
      "home_team": "St. Louis Blues",
      "home_score": "5",
      "away_team": "Seattle Kraken",
      "away_score": "1",
      "is_blowout": false
    },
    {
      "name": "Chicago Blackhawks at Nashville Predators",
      "short_name": "CHI @ NSH",
      "status": "Final",
      "sport": "nhl",
      "home_team": "Nashville Predators",
      "home_score": "4",
      "away_team": "Chicago Blackhawks",
      "away_score": "2",
      "is_blowout": false
    },
    {
      "name": "Minnesota Wild at Colorado Avalanche",
      "short_name": "MIN @ COL",
      "status": "Final",
      "sport": "nhl",
      "home_team": "Colorado Avalanche",
      "home_score": "2",
      "away_team": "Minnesota Wild",
      "away_score": "5",
      "is_blowout": false
    },
    {
      "name": "Detroit Tigers at Baltimore Orioles",
      "short_name": "DET @ BAL",
      "status": "Final",
      "sport": "mlb",
      "home_team": "Baltimore Orioles",
      "home_score": "6",
      "away_team": "Detroit Tigers",
      "away_score": "5",
      "is_blowout": false
    },
    {
      "name": "Tampa Bay Rays at Boston Red Sox",
      "short_name": "TB @ BOS",
      "status": "Final",
      "sport": "mlb",
      "home_team": "Boston Red Sox",
      "home_score": "7",
      "away_team": "Tampa Bay Rays",
      "away_score": "5",
      "is_blowout": false
    },
    {
      "name": "New York Mets at Houston Astros",
      "short_name": "NYM @ HOU",
      "status": "Final",
      "sport": "mlb",
      "home_team": "Houston Astros",
      "home_score": "0",
      "away_team": "New York Mets",
      "away_score": "5",
      "is_blowout": false
    },
    {
      "name": "Atlanta Braves at New York Yankees",
      "short_name": "ATL @ NYY",
      "status": "Final",
      "sport": "mlb",
      "home_team": "New York Yankees",
      "home_score": "7",
      "away_team": "Atlanta Braves",
      "away_score": "3",
      "is_blowout": false
    },
    {
      "name": "Washington Nationals at Philadelphia Phillies",
      "short_name": "WSH @ PHI",
      "status": "Final",
      "sport": "mlb",
      "home_team": "Philadelphia Phillies",
      "home_score": "7",
      "away_team": "Washington Nationals",
      "away_score": "3",
      "is_blowout": false
    },
    {
      "name": "Minnesota Twins at Pittsburgh Pirates",
      "short_name": "MIN @ PIT",
      "status": "Final",
      "sport": "mlb",
      "home_team": "Pittsburgh Pirates",
      "home_score": "6",
      "away_team": "Minnesota Twins",
      "away_score": "4",
      "is_blowout": false
    },
    {
      "name": "Houston Astros at St. Louis Cardinals",
      "short_name": "HOU @ STL",
      "status": "Final",
      "sport": "mlb",
      "home_team": "St. Louis Cardinals",
      "home_score": "9",
      "away_team": "Houston Astros",
      "away_score": "4",
      "is_blowout": false
    },
    {
      "name": "Miami Marlins at Toronto Blue Jays",
      "short_name": "MIA @ TOR",
      "status": "Final",
      "sport": "mlb",
      "home_team": "Toronto Blue Jays",
      "home_score": "7",
      "away_team": "Miami Marlins",
      "away_score": "8",
      "is_blowout": false
    },
    {
      "name": "Texas Rangers at Athletics Athletics",
      "short_name": "TEX @ ATH",
      "status": "Final",
      "sport": "mlb",
      "home_team": "Athletics",
      "home_score": "7",
      "away_team": "Texas Rangers",
      "away_score": "3",
      "is_blowout": false
    },
    {
      "name": "San Diego Padres at Cincinnati Reds",
      "short_name": "SD @ CIN",
      "status": "Final",
      "sport": "mlb",
      "home_team": "Cincinnati Reds",
      "home_score": "11",
      "away_team": "San Diego Padres",
      "away_score": "10",
      "is_blowout": false
    },
    {
      "name": "Michigan State Spartans at Purdue Boilermakers",
      "short_name": "MSU @ PUR",
      "status": "Final",
      "sport": "ncaab",
      "home_team": "Purdue Boilermakers",
      "home_score": "74",
      "away_team": "Michigan State Spartans",
      "away_score": "76",
      "is_blowout": false
    },
    {
      "name": "North Carolina Tar Heels at TCU Horned Frogs",
      "short_name": "UNC VS TCU",
      "status": "Scheduled",
      "sport": "ncaaf",
      "home_team": "TCU Horned Frogs",
      "home_score": "0",
      "away_team": "North Carolina Tar Heels",
      "away_score": "0",
      "is_blowout": false
    },
    {
      "name": "Hawai'i Rainbow Warriors at Stanford Cardinal",
      "short_name": "HAW @ STAN",
      "status": "Scheduled",
      "sport": "ncaaf",
      "home_team": "Stanford Cardinal",
      "home_score": "0",
      "away_team": "Hawai'i Rainbow Warriors",
      "away_score": "0",
      "is_blowout": false
    },
    {
      "name": "NC State Wolfpack at Virginia Cavaliers",
      "short_name": "NCSU VS UVA",
      "status": "Scheduled",
      "sport": "ncaaf",
      "home_team": "Virginia Cavaliers",
      "home_score": "0",
      "away_team": "NC State Wolfpack",
      "away_score": "0",
      "is_blowout": false
    },
    {
      "name": "New Mexico State Aggies at Florida State Seminoles",
      "short_name": "NMSU @ FSU",
      "status": "Scheduled",
      "sport": "ncaaf",
      "home_team": "Florida State Seminoles",
      "home_score": "0",
      "away_team": "New Mexico State Aggies",
      "away_score": "0",
      "is_blowout": false
    },
    {
      "name": "Memphis Tigers at UNLV Rebels",
      "short_name": "MEM @ UNLV",
      "status": "Scheduled",
      "sport": "ncaaf",
      "home_team": "UNLV Rebels",
      "home_score": "0",
      "away_team": "Memphis Tigers",
      "away_score": "0",
      "is_blowout": false
    },
    {
      "name": "Bethune-Cookman Wildcats at UCF Knights",
      "short_name": "BCU @ UCF",
      "status": "Scheduled",
      "sport": "ncaaf",
      "home_team": "UCF Knights",
      "home_score": "0",
      "away_team": "Bethune-Cookman Wildcats",
      "away_score": "0",
      "is_blowout": false
    },
    {
      "name": "Idaho Vandals at Utah Utes",
      "short_name": "IDHO @ UTAH",
      "status": "Scheduled",
      "sport": "ncaaf",
      "home_team": "Utah Utes",
      "home_score": "0",
      "away_team": "Idaho Vandals",
      "away_score": "0",
      "is_blowout": false
    },
    {
      "name": "Colorado Buffaloes at Georgia Tech Yellow Jackets",
      "short_name": "COLO @ GT",
      "status": "Scheduled",
      "sport": "ncaaf",
      "home_team": "Georgia Tech Yellow Jackets",
      "home_score": "0",
      "away_team": "Colorado Buffaloes",
      "away_score": "0",
      "is_blowout": false
    },
    {
      "name": "Akron Zips at Wake Forest Demon Deacons",
      "short_name": "AKR @ WAKE",
      "status": "Scheduled",
      "sport": "ncaaf",
      "home_team": "Wake Forest Demon Deacons",
      "home_score": "0",
      "away_team": "Akron Zips",
      "away_score": "0",
      "is_blowout": false
    },
    {
      "name": "Eastern Illinois Panthers at Minnesota Golden Gophers",
      "short_name": "EIU @ MINN",
      "status": "Scheduled",
      "sport": "ncaaf",
      "home_team": "Minnesota Golden Gophers",
      "home_score": "0",
      "away_team": "Eastern Illinois Panthers",
      "away_score": "0",
      "is_blowout": false
    }
  ],
  "headlines": [
    {
      "headline": "Why Windy isn't surprised 'flawed' Lakers lost to Suns",
      "description": "Brian Windhorst reacts to the Lakers' latest loss and what it could mean for their future.",
      "sport": "nba"
    },
    {
      "headline": "Does the East have a true favorite? Execs, coaches, scouts weigh in",
      "description": "Tim Bontemps and Brian Windhorst survey the league to see who has the edge in the wide-open Eastern Conference.",
      "sport": "nba"
    },
    {
      "headline": "'He earned every minute': How Isaiah Stewart became Detroit's enforcer",
      "description": "The intimidation, the electric blocks -- and, yes, even the suspensions -- are all part of the Beef Stew experience.",
      "sport": "nba"
    },
    {
      "headline": "Brooklyn faces Boston on 6-game skid",
      "description": "Brooklyn Nets (15-43, 14th in the Eastern Conference) vs. Boston Celtics (38-20, second in the Eastern Conference)",
      "sport": "nba"
    },
    {
      "headline": "Dallas plays Memphis, looks to break home losing streak",
      "description": "Memphis Grizzlies (21-36, 11th in the Western Conference) vs. Dallas Mavericks (21-37, 12th in the Western Conference)",
      "sport": "nba"
    },
    {
      "headline": "Bey leads New Orleans against Utah after 42-point game",
      "description": "New Orleans Pelicans (18-42, 14th in the Western Conference) vs. Utah Jazz (18-41, 13th in the Western Conference)",
      "sport": "nba"
    },
    {
      "headline": "Ty Simpson wants to show he's franchise QB at NFL combine",
      "description": "Former Alabama quarterback Ty Simpson said Friday at the NFL's scouting combine that he's prepared to show NFL talent evaluators that he is a \"franchise quarterback.''",
      "sport": "nfl"
    },
    {
      "headline": "Sources: Cowboys to place franchise tag on WR George Pickens",
      "description": "The Cowboys will do what has been expected on Friday, placing the franchise tag on receiver George Pickens to secure his rights at least through 2026, sources tell ESPN.",
      "sport": "nfl"
    },
    {
      "headline": "QB Mendoza meets with Raiders, loves idea of Brady as mentor",
      "description": "Quarterback Fernando Mendoza, the presumptive top pick in April's NFL draft, met with the Raiders at the combine Friday and loves the idea of having seven-time Super Bowl champion Tom Brady as a potential mentor.",
      "sport": "nfl"
    },
    {
      "headline": "Who holds the record for each NFL combine drill?",
      "description": "Revisit record-holders in each of the NFL combine drills: 40-yard dash, broad jump, bench press, and more.",
      "sport": "nfl"
    },
    {
      "headline": "Why Louis Riddick rates Ty Simpson so highly",
      "description": "Louis Riddick raves about why he thinks Ty Simpson has earned a spot as a top-15 pick in the 2026 NFL draft. ",
      "sport": "nfl"
    },
    {
      "headline": "Tannenbaum: Vikings should bring in Anthony Richardson",
      "description": "Mike Tannenbaum explains why he believes the Vikings' best option at quarterback is bringing in Anthony Richardson to compete with J.J. McCarthy.",
      "sport": "nfl"
    },
    {
      "headline": "NHL Power Rankings: New 1-32 poll, over/under bet for each team",
      "description": "As the NHL returns from the Olympic break, the rankings see big shifts beyond the top five.",
      "sport": "nhl"
    },
    {
      "headline": "Maple Leafs aim to break home skid in game against the Senators",
      "description": "Ottawa Senators (28-22-8, in the Atlantic Division) vs. Toronto Maple Leafs (27-23-9, in the Atlantic Division)",
      "sport": "nhl"
    },
    {
      "headline": "New York takes losing streak into game against Pittsburgh",
      "description": "Pittsburgh Penguins (30-15-12, in the Metropolitan Division) vs. New York Rangers (22-29-7, in the Metropolitan Division)",
      "sport": "nhl"
    },
    {
      "headline": "Stars host the Predators after Johnston's 2-goal game",
      "description": "Nashville Predators (27-24-7, in the Central Division) vs. Dallas Stars (35-14-9, in the Central Division)",
      "sport": "nhl"
    },
    {
      "headline": "Oilers visit the Sharks after Walman's 2-goal performance",
      "description": "Edmonton Oilers (29-23-8, in the Pacific Division) vs. San Jose Sharks (27-25-4, in the Pacific Division)",
      "sport": "nhl"
    },
    {
      "headline": "Red Wings visit the Hurricanes after Larkin's 2-goal game",
      "description": "Detroit Red Wings (34-19-6, in the Atlantic Division) vs. Carolina Hurricanes (37-15-6, in the Metropolitan Division)",
      "sport": "nhl"
    }
  ],
  "satire_angles": [
    {
      "type": "blowout_loss",
      "team": "Indiana Pacers",
      "description": "The Indiana Pacers got absolutely destroyed",
      "game": "Charlotte Hornets at Indiana Pacers",
      "sport": "nba"
    },
    {
      "type": "blowout_loss",
      "team": "Washington Wizards",
      "description": "The Washington Wizards got absolutely destroyed",
      "game": "Washington Wizards at Atlanta Hawks",
      "sport": "nba"
    },
    {
      "type": "blowout_loss",
      "team": "New England Patriots",
      "description": "The New England Patriots got absolutely destroyed",
      "game": "Seattle Seahawks at New England Patriots",
      "sport": "nfl"
    },
    {
      "type": "bad_beat",
      "description": "A heartbreaker decided by just 3 points",
      "game": "Los Angeles Lakers at Phoenix Suns",
      "sport": "nba"
    },
    {
      "type": "bad_beat",
      "description": "A heartbreaker decided by just 2 points",
      "game": "Columbus Blue Jackets at Boston Bruins",
      "sport": "nhl"
    },
    {
      "type": "bad_beat",
      "description": "A heartbreaker decided by just 1 points",
      "game": "New York Islanders at Montreal Canadiens",
      "sport": "nhl"
    },
    {
      "type": "bad_beat",
      "description": "A heartbreaker decided by just 1 points",
      "game": "Detroit Red Wings at Ottawa Senators",
      "sport": "nhl"
    },
    {
      "type": "bad_beat",
      "description": "A heartbreaker decided by just 3 points",
      "game": "New Jersey Devils at Pittsburgh Penguins",
      "sport": "nhl"
    },
    {
      "type": "bad_beat",
      "description": "A heartbreaker decided by just 1 points",
      "game": "Tampa Bay Lightning at Carolina Hurricanes",
      "sport": "nhl"
    },
    {
      "type": "bad_beat",
      "description": "A heartbreaker decided by just 1 points",
      "game": "Philadelphia Flyers at New York Rangers",
      "sport": "nhl"
    },
    {
      "type": "bad_beat",
      "description": "A heartbreaker decided by just 2 points",
      "game": "Chicago Blackhawks at Nashville Predators",
      "sport": "nhl"
    },
    {
      "type": "bad_beat",
      "description": "A heartbreaker decided by just 3 points",
      "game": "Minnesota Wild at Colorado Avalanche",
      "sport": "nhl"
    },
    {
      "type": "bad_beat",
      "description": "A heartbreaker decided by just 1 points",
      "game": "Detroit Tigers at Baltimore Orioles",
      "sport": "mlb"
    },
    {
      "type": "bad_beat",
      "description": "A heartbreaker decided by just 2 points",
      "game": "Tampa Bay Rays at Boston Red Sox",
      "sport": "mlb"
    },
    {
      "type": "bad_beat",
      "description": "A heartbreaker decided by just 2 points",
      "game": "Minnesota Twins at Pittsburgh Pirates",
      "sport": "mlb"
    },
    {
      "type": "bad_beat",
      "description": "A heartbreaker decided by just 1 points",
      "game": "Miami Marlins at Toronto Blue Jays",
      "sport": "mlb"
    },
    {
      "type": "bad_beat",
      "description": "A heartbreaker decided by just 1 points",
      "game": "San Diego Padres at Cincinnati Reds",
      "sport": "mlb"
    },
    {
      "type": "bad_beat",
      "description": "A heartbreaker decided by just 2 points",
      "game": "Michigan State Spartans at Purdue Boilermakers",
      "sport": "ncaab"
    },
    {
      "type": "injury_excuse",
      "description": "Does the East have a true favorite? Execs, coaches, scouts weigh in",
      "sport": "nba"
    }
  ],
  "suggested_topics": [
    "Why I Bet on Indiana Pacers and Now I'm Questioning My Life Choices",
    "The Bad Beat That Made Me Consider Selling a Kidney",
    "Injuries I'm Blaming for My Losing Streak (A Comprehensive List)"
  ]
}