{
  "site": "ballsdeep",
  "date": "2026-05-02",
  "gathered_at": "2026-05-02T15:59:55.316150",
  "status": "pending_processing",
  "games": [
    {
      "name": "Philadelphia 76ers at Boston Celtics",
      "short_name": "PHI @ BOS",
      "status": "Scheduled",
      "sport": "nba",
      "home_team": "Boston Celtics",
      "home_score": "0",
      "away_team": "Philadelphia 76ers",
      "away_score": "0",
      "is_blowout": false
    },
    {
      "name": "Seattle Seahawks at New England Patriots",
      "short_name": "SEA VS NE",
      "status": "Final",
      "sport": "nfl",
      "home_team": "New England Patriots",
      "home_score": "13",
      "away_team": "Seattle Seahawks",
      "away_score": "29",
      "is_blowout": true
    },
    {
      "name": "Philadelphia Flyers at Carolina Hurricanes",
      "short_name": "PHI @ CAR",
      "status": "Scheduled",
      "sport": "nhl",
      "home_team": "Carolina Hurricanes",
      "home_score": "0",
      "away_team": "Philadelphia Flyers",
      "away_score": "0",
      "is_blowout": false
    },
    {
      "name": "Baltimore Orioles at New York Yankees",
      "short_name": "BAL @ NYY",
      "status": "Scheduled",
      "sport": "mlb",
      "home_team": "New York Yankees",
      "home_score": "0",
      "away_team": "Baltimore Orioles",
      "away_score": "0",
      "is_blowout": false
    },
    {
      "name": "Toronto Blue Jays at Minnesota Twins",
      "short_name": "TOR @ MIN",
      "status": "Scheduled",
      "sport": "mlb",
      "home_team": "Minnesota Twins",
      "home_score": "0",
      "away_team": "Toronto Blue Jays",
      "away_score": "0",
      "is_blowout": false
    },
    {
      "name": "Arizona Diamondbacks at Chicago Cubs",
      "short_name": "ARI @ CHC",
      "status": "Scheduled",
      "sport": "mlb",
      "home_team": "Chicago Cubs",
      "home_score": "0",
      "away_team": "Arizona Diamondbacks",
      "away_score": "0",
      "is_blowout": false
    },
    {
      "name": "Cincinnati Reds at Pittsburgh Pirates",
      "short_name": "CIN @ PIT",
      "status": "Scheduled",
      "sport": "mlb",
      "home_team": "Pittsburgh Pirates",
      "home_score": "0",
      "away_team": "Cincinnati Reds",
      "away_score": "0",
      "is_blowout": false
    },
    {
      "name": "Milwaukee Brewers at Washington Nationals",
      "short_name": "MIL @ WSH",
      "status": "Scheduled",
      "sport": "mlb",
      "home_team": "Washington Nationals",
      "home_score": "0",
      "away_team": "Milwaukee Brewers",
      "away_score": "0",
      "is_blowout": false
    },
    {
      "name": "Cleveland Guardians at Athletics Athletics",
      "short_name": "CLE @ ATH",
      "status": "Scheduled",
      "sport": "mlb",
      "home_team": "Athletics",
      "home_score": "0",
      "away_team": "Cleveland Guardians",
      "away_score": "0",
      "is_blowout": false
    },
    {
      "name": "Houston Astros at Boston Red Sox",
      "short_name": "HOU @ BOS",
      "status": "Scheduled",
      "sport": "mlb",
      "home_team": "Boston Red Sox",
      "home_score": "0",
      "away_team": "Houston Astros",
      "away_score": "0",
      "is_blowout": false
    },
    {
      "name": "Philadelphia Phillies at Miami Marlins",
      "short_name": "PHI @ MIA",
      "status": "Scheduled",
      "sport": "mlb",
      "home_team": "Miami Marlins",
      "home_score": "0",
      "away_team": "Philadelphia Phillies",
      "away_score": "0",
      "is_blowout": false
    },
    {
      "name": "San Francisco Giants at Tampa Bay Rays",
      "short_name": "SF @ TB",
      "status": "Scheduled",
      "sport": "mlb",
      "home_team": "Tampa Bay Rays",
      "home_score": "0",
      "away_team": "San Francisco Giants",
      "away_score": "0",
      "is_blowout": false
    },
    {
      "name": "Texas Rangers at Detroit Tigers",
      "short_name": "TEX @ DET",
      "status": "Scheduled",
      "sport": "mlb",
      "home_team": "Detroit Tigers",
      "home_score": "0",
      "away_team": "Texas Rangers",
      "away_score": "0",
      "is_blowout": false
    },
    {
      "name": "UConn Huskies at Michigan Wolverines",
      "short_name": "CONN VS MICH",
      "status": "Final",
      "sport": "ncaab",
      "home_team": "Michigan Wolverines",
      "home_score": "69",
      "away_team": "UConn Huskies",
      "away_score": "63",
      "is_blowout": false
    },
    {
      "name": "North Carolina Tar Heels at TCU Horned Frogs",
      "short_name": "UNC VS TCU",
      "status": "Scheduled",
      "sport": "ncaaf",
      "home_team": "TCU Horned Frogs",
      "home_score": "0",
      "away_team": "North Carolina Tar Heels",
      "away_score": "0",
      "is_blowout": false
    },
    {
      "name": "Hawai'i Rainbow Warriors at Stanford Cardinal",
      "short_name": "HAW @ STAN",
      "status": "Scheduled",
      "sport": "ncaaf",
      "home_team": "Stanford Cardinal",
      "home_score": "0",
      "away_team": "Hawai'i Rainbow Warriors",
      "away_score": "0",
      "is_blowout": false
    },
    {
      "name": "NC State Wolfpack at Virginia Cavaliers",
      "short_name": "NCSU VS UVA",
      "status": "Scheduled",
      "sport": "ncaaf",
      "home_team": "Virginia Cavaliers",
      "home_score": "0",
      "away_team": "NC State Wolfpack",
      "away_score": "0",
      "is_blowout": false
    },
    {
      "name": "Memphis Tigers at UNLV Rebels",
      "short_name": "MEM @ UNLV",
      "status": "Scheduled",
      "sport": "ncaaf",
      "home_team": "UNLV Rebels",
      "home_score": "0",
      "away_team": "Memphis Tigers",
      "away_score": "0",
      "is_blowout": false
    },
    {
      "name": "San José State Spartans at USC Trojans",
      "short_name": "SJSU @ USC",
      "status": "Scheduled",
      "sport": "ncaaf",
      "home_team": "USC Trojans",
      "home_score": "0",
      "away_team": "San José State Spartans",
      "away_score": "0",
      "is_blowout": false
    },
    {
      "name": "New Mexico State Aggies at Florida State Seminoles",
      "short_name": "NMSU @ FSU",
      "status": "Scheduled",
      "sport": "ncaaf",
      "home_team": "Florida State Seminoles",
      "home_score": "0",
      "away_team": "New Mexico State Aggies",
      "away_score": "0",
      "is_blowout": false
    },
    {
      "name": "Jacksonville State Gamecocks at North Dakota State Bison",
      "short_name": "JVST @ NDSU",
      "status": "Scheduled",
      "sport": "ncaaf",
      "home_team": "North Dakota State Bison",
      "home_score": "0",
      "away_team": "Jacksonville State Gamecocks",
      "away_score": "0",
      "is_blowout": false
    },
    {
      "name": "Sacramento State Hornets at Eastern Michigan Eagles",
      "short_name": "SAC @ EMU",
      "status": "Scheduled",
      "sport": "ncaaf",
      "home_team": "Eastern Michigan Eagles",
      "home_score": "0",
      "away_team": "Sacramento State Hornets",
      "away_score": "0",
      "is_blowout": false
    },
    {
      "name": "Arkansas-Pine Bluff Golden Lions at Missouri Tigers",
      "short_name": "UAPB @ MIZ",
      "status": "Scheduled",
      "sport": "ncaaf",
      "home_team": "Missouri Tigers",
      "home_score": "0",
      "away_team": "Arkansas-Pine Bluff Golden Lions",
      "away_score": "0",
      "is_blowout": false
    },
    {
      "name": "Bethune-Cookman Wildcats at UCF Knights",
      "short_name": "BCU @ UCF",
      "status": "Scheduled",
      "sport": "ncaaf",
      "home_team": "UCF Knights",
      "home_score": "0",
      "away_team": "Bethune-Cookman Wildcats",
      "away_score": "0",
      "is_blowout": false
    }
  ],
  "headlines": [
    {
      "headline": "Betting tips, DFS picks for 76ers-Celtics: All of the factors in Game 7",
      "description": "Jim McCormick breaks down Saturday's Game 7 in Boston and offers his favorite bets and DFS plays.",
      "sport": "nba"
    },
    {
      "headline": "NBA playoffs 2026: Three Game 7s! What will decide each showdown",
      "description": "Not one, not two, but three Game 7s -- all in the East. Here are the keys to the 76ers-Celtics, Magic-Pistons and Raptors-Cavs.",
      "sport": "nba"
    },
    {
      "headline": "Celtics, 76ers set for winner-take-all game 7",
      "description": "Philadelphia 76ers (45-37, seventh in the Eastern Conference) vs. Boston Celtics (56-26, second in the Eastern Conference)",
      "sport": "nba"
    },
    {
      "headline": "Windy: Luka 'is not close' to returning",
      "description": "Brian Windhorst joins \"SportsCenter\" with Scott Van Pelt following the Lakers' Game 6 win over the Rockets to discuss Luka Doncic's potential return against the Thunder.",
      "sport": "nba"
    },
    {
      "headline": "Los Angeles Lakers vs. Houston Rockets: Game Highlights",
      "description": "Los Angeles Lakers vs. Houston Rockets: Game Highlights",
      "sport": "nba"
    },
    {
      "headline": "NBA offseason: Draft, free agency, trade targets for eliminated teams",
      "description": "Summer is here for 19 NBA franchises. What lies ahead for the Hawks, Blazers, Suns, Warriors and every eliminated team?",
      "sport": "nba"
    },
    {
      "headline": "Kentucky Derby mint juleps lead sports world's signature food, drink staples",
      "description": "The bourbon-based cocktail is a Churchill Downs staple, but the Kentucky Derby isn't the only event associated with a signature food or beverage item.",
      "sport": "nfl"
    },
    {
      "headline": "Postdraft questions for the Chargers' top picks",
      "description": "Joe Hortiz went down the list of the Chargers' needs in the 2026 NFL draft. But there are still questions.",
      "sport": "nfl"
    },
    {
      "headline": "Pay C.J. Stroud? NFL execs from around the league weigh in",
      "description": "After paying Will Anderson, will Houston do the same with its franchise quarterback?",
      "sport": "nfl"
    },
    {
      "headline": "Dolphins making 'no apologies' for drafting Proctor over Downs, Bain",
      "description": "Dolphins general manager Jon-Eric Sullivan said the team's decision wasn't about a lack of belief for either Downs or Bain.",
      "sport": "nfl"
    },
    {
      "headline": "Inside the Seahawks' strategy to draft competitors",
      "description": "What did Jadarian Price, Bud Clark and six other Seattle picks have in common?",
      "sport": "nfl"
    },
    {
      "headline": "Our midseason look at the UFL: How have new rules fared?",
      "description": "Taking a closer look at some of the trends, rule changes and other takeaways from the start of Mike Repole's first season with the league.",
      "sport": "nfl"
    },
    {
      "headline": "Philadelphia Flyers fan returns Cam York's stick from game-winning goal",
      "description": "Philadelphia Flyers defenseman Cam York hurled his stick into the crowd after his game-winning goal against the Penguins.",
      "sport": "nhl"
    },
    {
      "headline": "Stanley Cup playoffs daily: Previews, stats, schedule, bracket",
      "description": "Round 2 is set to begin. Here are keys to the series, along with recaps of Friday's thrillers and updated stats.",
      "sport": "nhl"
    },
    {
      "headline": "Stanley Cup playoffs 2026: Bracket, schedule, scores, news",
      "description": "From the first round all the way through the Stanley Cup Final, ESPN has you covered this NHL postseason.",
      "sport": "nhl"
    },
    {
      "headline": "NHL teams' offseason keys, including free agency, draft needs",
      "description": "We explore the next moves each team should make this summer and forecast expectations for 2026-27.",
      "sport": "nhl"
    },
    {
      "headline": "Avalanche and Wild square off to start the second round",
      "description": "Minnesota Wild (46-24-12, in the Central Division) vs. Colorado Avalanche (55-16-11, in the Central Division)",
      "sport": "nhl"
    },
    {
      "headline": "Vegas Golden Knights vs. Utah Mammoth: Game Highlights",
      "description": "Vegas Golden Knights vs. Utah Mammoth: Game Highlights",
      "sport": "nhl"
    }
  ],
  "satire_angles": [
    {
      "type": "blowout_loss",
      "team": "New England Patriots",
      "description": "The New England Patriots got absolutely destroyed",
      "game": "Seattle Seahawks at New England Patriots",
      "sport": "nfl"
    },
    {
      "type": "roster_move",
      "description": "NBA offseason: Draft, free agency, trade targets for eliminated teams",
      "sport": "nba"
    },
    {
      "type": "roster_move",
      "description": "Kentucky Derby mint juleps lead sports world's signature food, drink staples",
      "sport": "nfl"
    }
  ],
  "suggested_topics": [
    "Why I Bet on New England Patriots and Now I'm Questioning My Life Choices"
  ]
}