{
  "site": "mlb_sites",
  "target_sites": [
    {
      "name": "dailymlbpicks",
      "angle": "AI predictions, beginner-friendly, futures focus"
    },
    {
      "name": "mlbprediction",
      "angle": "Analytics, advanced stats (xBA, WAR, xFIP), data-driven"
    },
    {
      "name": "bestmlbhandicapper",
      "angle": "Sharp money, expert handicapping, situational angles"
    }
  ],
  "date": "2026-01-30",
  "gathered_at": "2026-01-30T15:42:46.489499",
  "status": "pending_processing",
  "news_items": [
    {
      "headline": "ESPN Fantasy: Everything you need to know about player position eligibility rules",
      "description": "Which players qualify at which positions for 2026 and beyond? Tristan H. Cockcroft explains the rules.",
      "published": "2026-01-30T12:25:44Z",
      "type": "Story",
      "categories": [
        "fantasy",
        "news - fantasy baseball",
        "MLB",
        "news - fantasy",
        "Fantasy MLB",
        "",
        "",
        "",
        "",
        ""
      ]
    },
    {
      "headline": "MLB 2026: Inside Driveline's hitting lab",
      "description": "We got an all-access pass to a two-day MLB training session in Scottsdale, Arizona.",
      "published": "2026-01-30T11:40:00Z",
      "type": "Story",
      "categories": [
        "Shohei Ohtani",
        "MLB",
        "Edgar Quero",
        "",
        "",
        ""
      ]
    },
    {
      "headline": "Getz, Venable say White Sox enter '26 season with 'momentum'",
      "description": "White Sox GM Chris Getz and manager Will Venable believe they have a group poised to build on the progress it showed last season, when the team improved by 19 wins over the 2024 season.",
      "published": "2026-01-30T03:18:08Z",
      "type": "HeadlineNews",
      "categories": [
        "news",
        "MLB",
        "Chicago White Sox",
        "",
        "",
        ""
      ]
    },
    {
      "headline": "Austin Gomber signs minor league contract with Rangers",
      "description": "Veteran left-hander Austin Gomber has signed a minor league contract with the Texas Rangers that includes an invitation to major league spring training.",
      "published": "2026-01-29T21:04:07Z",
      "type": "HeadlineNews",
      "categories": [
        "Austin Gomber",
        "Texas Rangers",
        "MLB",
        "",
        "",
        ""
      ]
    },
    {
      "headline": "Mets sign Craig Kimbrel, Austin Barnes to minor league deals",
      "description": "The New York Mets signed reliever Craig Kimbrel to a minor league contract Thursday with an invitation to big league spring training, giving the nine-time All-Star an opportunity to pitch for his 10th different team should he make the club.",
      "published": "2026-01-29T21:45:03Z",
      "type": "HeadlineNews",
      "categories": [
        "Craig Kimbrel",
        "news",
        "Austin Barnes",
        "New York Mets",
        "MLB",
        "",
        "",
        "",
        "",
        ""
      ]
    },
    {
      "headline": "Fantasy baseball news or noise: 30/30 for Evan Carter? Is Bryce Miller a heavy sleeper?",
      "description": "Eric Karabell keeps tabs on the baseball world and tells you what is relevant to fantasy baseball managers.",
      "published": "2026-01-29T18:57:41Z",
      "type": "Story",
      "categories": [
        "Edouard Julien",
        "fantasy",
        "Lars Nootbaar",
        "MLB",
        "Bryce Miller",
        "news - fantasy",
        "Evan Carter",
        "Eric Karabell",
        "news - fantasy baseball",
        "Fantasy MLB",
        "",
        "",
        "",
        "",
        "",
        "",
        "",
        "",
        "",
        ""
      ]
    }
  ],
  "transactions": [],
  "teams": [
    {
      "name": "Arizona Diamondbacks",
      "abbreviation": "ARI",
      "location": "Arizona"
    },
    {
      "name": "Athletics",
      "abbreviation": "ATH",
      "location": "Athletics"
    },
    {
      "name": "Atlanta Braves",
      "abbreviation": "ATL",
      "location": "Atlanta"
    },
    {
      "name": "Baltimore Orioles",
      "abbreviation": "BAL",
      "location": "Baltimore"
    },
    {
      "name": "Boston Red Sox",
      "abbreviation": "BOS",
      "location": "Boston"
    },
    {
      "name": "Chicago Cubs",
      "abbreviation": "CHC",
      "location": "Chicago"
    },
    {
      "name": "Chicago White Sox",
      "abbreviation": "CHW",
      "location": "Chicago"
    },
    {
      "name": "Cincinnati Reds",
      "abbreviation": "CIN",
      "location": "Cincinnati"
    },
    {
      "name": "Cleveland Guardians",
      "abbreviation": "CLE",
      "location": "Cleveland"
    },
    {
      "name": "Colorado Rockies",
      "abbreviation": "COL",
      "location": "Colorado"
    },
    {
      "name": "Detroit Tigers",
      "abbreviation": "DET",
      "location": "Detroit"
    },
    {
      "name": "Houston Astros",
      "abbreviation": "HOU",
      "location": "Houston"
    },
    {
      "name": "Kansas City Royals",
      "abbreviation": "KC",
      "location": "Kansas City"
    },
    {
      "name": "Los Angeles Angels",
      "abbreviation": "LAA",
      "location": "Los Angeles"
    },
    {
      "name": "Los Angeles Dodgers",
      "abbreviation": "LAD",
      "location": "Los Angeles"
    },
    {
      "name": "Miami Marlins",
      "abbreviation": "MIA",
      "location": "Miami"
    },
    {
      "name": "Milwaukee Brewers",
      "abbreviation": "MIL",
      "location": "Milwaukee"
    },
    {
      "name": "Minnesota Twins",
      "abbreviation": "MIN",
      "location": "Minnesota"
    },
    {
      "name": "New York Mets",
      "abbreviation": "NYM",
      "location": "New York"
    },
    {
      "name": "New York Yankees",
      "abbreviation": "NYY",
      "location": "New York"
    },
    {
      "name": "Philadelphia Phillies",
      "abbreviation": "PHI",
      "location": "Philadelphia"
    },
    {
      "name": "Pittsburgh Pirates",
      "abbreviation": "PIT",
      "location": "Pittsburgh"
    },
    {
      "name": "San Diego Padres",
      "abbreviation": "SD",
      "location": "San Diego"
    },
    {
      "name": "San Francisco Giants",
      "abbreviation": "SF",
      "location": "San Francisco"
    },
    {
      "name": "Seattle Mariners",
      "abbreviation": "SEA",
      "location": "Seattle"
    },
    {
      "name": "St. Louis Cardinals",
      "abbreviation": "STL",
      "location": "St. Louis"
    },
    {
      "name": "Tampa Bay Rays",
      "abbreviation": "TB",
      "location": "Tampa Bay"
    },
    {
      "name": "Texas Rangers",
      "abbreviation": "TEX",
      "location": "Texas"
    },
    {
      "name": "Toronto Blue Jays",
      "abbreviation": "TOR",
      "location": "Toronto"
    },
    {
      "name": "Washington Nationals",
      "abbreviation": "WSH",
      "location": "Washington"
    }
  ],
  "extracted_players": [
    "Eric Karabell",
    "Austin Gomber",
    "Texas Rangers",
    "Craig Kimbrel",
    "White Sox",
    "Austin Barnes",
    "Evan Carter",
    "Inside Driveline",
    "Rangers Veteran",
    "Will Venable",
    "Is Bryce Miller",
    "Chris Getz"
  ],
  "extracted_contracts": [],
  "key_storylines": [
    {
      "headline": "ESPN Fantasy: Everything you need to know about player position eligibility rules",
      "description": "Which players qualify at which positions for 2026 and beyond? Tristan H. Cockcroft explains the rules.",
      "categories": [
        "fantasy",
        "news - fantasy baseball",
        "MLB",
        "news - fantasy",
        "Fantasy MLB",
        "",
        "",
        "",
        "",
        ""
      ]
    },
    {
      "headline": "MLB 2026: Inside Driveline's hitting lab",
      "description": "We got an all-access pass to a two-day MLB training session in Scottsdale, Arizona.",
      "categories": [
        "Shohei Ohtani",
        "MLB",
        "Edgar Quero",
        "",
        "",
        ""
      ]
    },
    {
      "headline": "Getz, Venable say White Sox enter '26 season with 'momentum'",
      "description": "White Sox GM Chris Getz and manager Will Venable believe they have a group poised to build on the progress it showed last season, when the team improved by 19 wins over the 2024 season.",
      "categories": [
        "news",
        "MLB",
        "Chicago White Sox",
        "",
        "",
        ""
      ]
    },
    {
      "headline": "Austin Gomber signs minor league contract with Rangers",
      "description": "Veteran left-hander Austin Gomber has signed a minor league contract with the Texas Rangers that includes an invitation to major league spring training.",
      "categories": [
        "Austin Gomber",
        "Texas Rangers",
        "MLB",
        "",
        "",
        ""
      ]
    },
    {
      "headline": "Mets sign Craig Kimbrel, Austin Barnes to minor league deals",
      "description": "The New York Mets signed reliever Craig Kimbrel to a minor league contract Thursday with an invitation to big league spring training, giving the nine-time All-Star an opportunity to pitch for his 10th different team should he make the club.",
      "categories": [
        "Craig Kimbrel",
        "news",
        "Austin Barnes",
        "New York Mets",
        "MLB",
        "",
        "",
        "",
        "",
        ""
      ]
    }
  ]
}